mux2_4.v
module mux2_4(output wire [3:0] Out, input wire [3:0] A, input wire [3:0] B, input wire s); 
    /*     wire  mux1_out;
    wire  mux2_out;
    wire  mux3_out;
    wire  mux4_out; */
    /*     mux2_1_i3 mux_1(mux1_out , A[0] , B[0] , s);
    mux2_1_i3 mux_2(mux2_out , A[1] , B[1] , s);
    mux2_1_i3 mux_3(mux3_out , A[2] , B[2] , s);
    mux2_1_i3 mux_4(mux4_out , A[3] , B[3] , s); */

    assign Out = s ? B : A;
    /*     assign Out = {mux4_out, mux3_out, mux2_out, mux1_out};
    */    
 endmodule

mux4.v

module mux4(output reg out, input wire a, b, c, d, input wire [1:0] S);

    always @(*)
    begin
    case (S)
        2'b00: out = a;
        2'b01: out = b;
        2'b10: out = c;
        2'b11: out = d;
    endcase
    end

endmodule

modificacion/cl.v
module cl(output wire out, input wire a, b, input wire [1:0] S);

  wire and_, or_, xor_, inv_;

  and and1 (and_, a, b);
  or or1 (or_, a, b);
  xor xor1 (xor_, a, b);
  not not1 (inv_, a);

  mux4 mux1 (out, and_, or_, xor_, inv_, S);

endmodule

ul4.v
module ul4(output wire[3:0] Out, input wire[3:0] A, input wire[3:0] B, input wire [1:0] S);//unidad logica estructural

//uso dos cl para hacer toda la estructural

  cl cl1 (Out[0], A[0], B[0], S);
  cl cl2 (Out[1], A[1], B[1], S);
  cl cl3 (Out[2], A[2], B[2], S);
  cl cl4 (Out[3], A[3], B[3], S);
  
endmodule

sum4_v2.v
module sum4_v2(output wire[3:0] S, output wire c_out, input wire[3:0] A, input wire[3:0] B, input wire c_in); 

  assign {c_out, S} = A + B + c_in;

endmodule

compl1.v
module compl1(output wire [3:0] Out, input wire [3:0] Inp, input wire cpl); 

/* wire [3:0] temp;

not not1(temp[0], Inp[0]);
not not2(temp[1], Inp[1]);
not not3(temp[2], Inp[2]);
not not4(temp[3], Inp[3]);

mux2_4 mux1(Out, Inp, temp, cpl); */

  assign Out = cpl ? ~Inp : Inp;




endmodule

alu.v
module alu(output wire [3:0] R, output wire zero, c_out, sign, input wire [3:0] A, B, input wire c_in, input wire [1:0] ALUOP, input wire l);

//constantes
/* reg [3:0] cero = 4'b0000;
reg [3:0] uno = 4'b0001; */

  //tabla de excel
  wire add1;
  wire op_1;
  wire op_2;
  wire cpl;

  assign add1 = ALUOP[0];
  assign op_1 = ((l) | (ALUOP[1] & ~ALUOP[0])); 
  assign op_2 = ((l) | (ALUOP[1] & ~ALUOP[0])); 
  assign cpl = (~l & ~ALUOP[1] & ALUOP[0]);

  //cables de conexion
  wire [3:0] arriba;
  wire [3:0] abajo;
  wire [3:0] OP1;
  wire [3:0] OP2;
  wire [3:0] sum4_out;
  wire [3:0] ul4_out;

  //parte de arriba izquierda
  mux2_4 mux_1 (arriba, 4'b0000, 4'b0001, add1);
  mux2_4 mux_3 (OP1, arriba, A, op_1);

  //parte de abajo izquierda
  mux2_4 mux_2 (abajo, A, B, op_2);
  compl1 compl_1 (OP2, abajo, cpl); 

  //parte sum4
  sum4_v2 sum_1 (sum4_out, c_out, OP1, OP2, c_in);

  //parte ul4
  ul4 ul_4 (ul4_out, OP1, OP2, ALUOP);

  //parte final
  mux2_4 mux_4 (R, sum4_out, ul4_out, l);

  //zero, carry y sign  
  assign zero = ~R[3] & ~R[2] & ~R[1] & ~R[0];
  assign sign = l ? 1'bx : R[3];


endmodule

modificacion/alu_tb.v
`timescale 1 ns / 10 ps //Directiva que fija la unidad de tiempo de simulación y la precision de la unidad
module alu_tb;
//declaracion de señales
reg [1:0] t_Op;
reg t_l, t_cin;
reg [3:0] t_A, t_B; 
wire [3:0] t_R;
wire t_z, t_c, t_s;
integer errores;

// error de cualquier tipo, de resultado, de linea zero, de signo y carry
reg error, error_R, error_z, error_s, error_c; 

//instancia del modulo a testear
alu mat(t_R, t_z, t_c, t_s, t_A, t_B, t_cin, t_Op, t_l);


initial
begin
	$dumpfile("alu.vcd");
	$dumpvars;

	errores = 0;
	t_l = 1'b0;
	repeat(2)
	begin
		t_Op = 2'b0;
		repeat(4)
		begin
			t_cin = 1'b0;
			repeat(2)
			begin
		    	t_A = 4'b0;
		    	repeat(16) 
		    	begin
					t_B = 4'b0;
					repeat(16) 
			  		begin
						#0.01 check;
						#9.99;
						t_B = t_B + 1;
			  		end
			  		t_A = t_A + 1;
		    	end
				t_cin = t_cin + 1;
			end
			t_Op = t_Op + 1;
		end
		t_l = t_l + 1;
	end
	$display("Encontradas %d operaciones erroneas", errores);
  	//fin simulacion
  	$finish;
end

// Tarea para hacer la comprobación automática de resultados
task check;
reg [4:0] expected_R;
reg expected_z, expected_c, expected_s;

begin
	$write("tiempo=%0d A=%b B=%b c_in=%b L=%b OP=%b R=%b, Z=%b, C=%b, S=%b.", $time, t_A, t_B, t_cin, t_l, t_Op, t_R, t_z, t_c, t_s);

	// Si las operaciones son lógicas
	if (t_l)
	begin
		case (t_Op)
			2'b00: expected_R[3:0] = t_A & t_B;
			2'b01: expected_R[3:0] = t_A | t_B;
			2'b10: expected_R[3:0] = t_A ^ t_B;
			2'b11: expected_R[3:0] = ~t_A;
			default: $display("ERROR. Valor no esperado para t_Op: %b", t_Op);
		endcase
		// Se establece a 0, pero realmente es un "don't care"
		expected_c = 1'b0;
		expected_s = expected_R[3];
		// las operaciones lógicas no pueden tener error de signo o acarreo
		error_s = 0;
	 	error_c = 0;
	end
	else
	begin
		case (t_Op)
			2'b00: expected_R = (t_A ^4'b1111) + 4'b0001 + t_cin;
			2'b01: expected_R = (t_B ^4'b1111) + 4'b0001 + t_cin;
			2'b10: expected_R = t_A + t_B + t_cin;
			2'b11: expected_R = t_A + 1 + t_cin;
			default: $display("ERROR. Valor no esperado para t_Op: %b", t_Op);
		endcase
		expected_c = expected_R[4];
		expected_s = expected_R[3];
		// generacion señales error específicas operaciones aritmeticas
		error_s = (expected_s !== t_s);
	 	error_c = (expected_c !== t_c);
	end

	expected_z = ~| expected_R[3:0];
	// generacion señales error generales para toda la ALU
	error_R = (expected_R[3:0] !== t_R); 
	error_z = (expected_z !== t_z);
	error = error_R | error_z | error_s | error_c;
	if (error)
	begin
		errores = errores + 1;
		$display(" ---- ERROR");
		if (error_R)
			$display("\tResultado esperado %b, obtenido %b", expected_R[3:0], t_R);
		if (error_z)
			$display("\tFlag de cero esperado %b, obtenido %b", expected_z, t_z);
		if (error_s)
			$display("\tFlag de signo esperado %b, obtenido %b", expected_s, t_s);
		if (error_c)
			$display("\tFlag de acarreo esperado %b, obtenido %b", expected_c, t_c);
	end
	else
		$display(" ---- OK");
end
endtask
endmodule

alu.vcd
$date
	Sun Oct 22 20:20:20 2023
$end
$version
	Icarus Verilog
$end
$timescale
	10ps
$end
$scope module alu_tb $end
$var wire 1 ! t_z $end
$var wire 1 " t_s $end
$var wire 1 # t_c $end
$var wire 4 $ t_R [3:0] $end
$var reg 1 % error $end
$var reg 1 & error_R $end
$var reg 1 ' error_c $end
$var reg 1 ( error_s $end
$var reg 1 ) error_z $end
$var reg 4 * t_A [3:0] $end
$var reg 4 + t_B [3:0] $end
$var reg 2 , t_Op [1:0] $end
$var reg 1 - t_cin $end
$var reg 1 . t_l $end
$var integer 32 / errores [31:0] $end
$scope module mat $end
$var wire 4 0 A [3:0] $end
$var wire 2 1 ALUOP [1:0] $end
$var wire 4 2 B [3:0] $end
$var wire 1 - c_in $end
$var wire 1 3 cpl $end
$var wire 1 . l $end
$var wire 1 4 op_1 $end
$var wire 1 5 op_2 $end
$var wire 1 ! zero $end
$var wire 4 6 ul4_out [3:0] $end
$var wire 4 7 sum4_out [3:0] $end
$var wire 1 " sign $end
$var wire 1 # c_out $end
$var wire 4 8 arriba [3:0] $end
$var wire 1 9 add1 $end
$var wire 4 : abajo [3:0] $end
$var wire 4 ; R [3:0] $end
$var wire 4 < OP2 [3:0] $end
$var wire 4 = OP1 [3:0] $end
$scope module compl_1 $end
$var wire 1 3 cpl $end
$var wire 4 > Out [3:0] $end
$var wire 4 ? Inp [3:0] $end
$upscope $end
$scope module mux_1 $end
$var wire 4 @ A [3:0] $end
$var wire 4 A B [3:0] $end
$var wire 1 9 s $end
$var wire 4 B Out [3:0] $end
$upscope $end
$scope module mux_2 $end
$var wire 4 C A [3:0] $end
$var wire 4 D B [3:0] $end
$var wire 1 5 s $end
$var wire 4 E Out [3:0] $end
$upscope $end
$scope module mux_3 $end
$var wire 4 F A [3:0] $end
$var wire 4 G B [3:0] $end
$var wire 1 4 s $end
$var wire 4 H Out [3:0] $end
$upscope $end
$scope module mux_4 $end
$var wire 1 . s $end
$var wire 4 I Out [3:0] $end
$var wire 4 J B [3:0] $end
$var wire 4 K A [3:0] $end
$upscope $end
$scope module sum_1 $end
$var wire 4 L A [3:0] $end
$var wire 4 M B [3:0] $end
$var wire 1 - c_in $end
$var wire 1 # c_out $end
$var wire 4 N S [3:0] $end
$upscope $end
$scope module ul_4 $end
$var wire 4 O A [3:0] $end
$var wire 4 P B [3:0] $end
$var wire 2 Q S [1:0] $end
$var wire 4 R Out [3:0] $end
$scope module cl1 $end
$var wire 2 S S [1:0] $end
$var wire 1 T a $end
$var wire 1 U and_ $end
$var wire 1 V b $end
$var wire 1 W inv_ $end
$var wire 1 X or_ $end
$var wire 1 Y xor_ $end
$var wire 1 Z out $end
$scope module mux1 $end
$var wire 2 [ S [1:0] $end
$var wire 1 U a $end
$var wire 1 X b $end
$var wire 1 Y c $end
$var wire 1 W d $end
$var reg 1 Z out $end
$upscope $end
$upscope $end
$scope module cl2 $end
$var wire 2 \ S [1:0] $end
$var wire 1 ] a $end
$var wire 1 ^ and_ $end
$var wire 1 _ b $end
$var wire 1 ` inv_ $end
$var wire 1 a or_ $end
$var wire 1 b xor_ $end
$var wire 1 c out $end
$scope module mux1 $end
$var wire 2 d S [1:0] $end
$var wire 1 ^ a $end
$var wire 1 a b $end
$var wire 1 b c $end
$var wire 1 ` d $end
$var reg 1 c out $end
$upscope $end
$upscope $end
$scope module cl3 $end
$var wire 2 e S [1:0] $end
$var wire 1 f a $end
$var wire 1 g and_ $end
$var wire 1 h b $end
$var wire 1 i inv_ $end
$var wire 1 j or_ $end
$var wire 1 k xor_ $end
$var wire 1 l out $end
$scope module mux1 $end
$var wire 2 m S [1:0] $end
$var wire 1 g a $end
$var wire 1 j b $end
$var wire 1 k c $end
$var wire 1 i d $end
$var reg 1 l out $end
$upscope $end
$upscope $end
$scope module cl4 $end
$var wire 2 n S [1:0] $end
$var wire 1 o a $end
$var wire 1 p and_ $end
$var wire 1 q b $end
$var wire 1 r inv_ $end
$var wire 1 s or_ $end
$var wire 1 t xor_ $end
$var wire 1 u out $end
$scope module mux1 $end
$var wire 2 v S [1:0] $end
$var wire 1 p a $end
$var wire 1 s b $end
$var wire 1 t c $end
$var wire 1 r d $end
$var reg 1 u out $end
$upscope $end
$upscope $end
$upscope $end
$upscope $end
$scope task check $end
$var reg 5 w expected_R [4:0] $end
$var reg 1 x expected_c $end
$var reg 1 y expected_s $end
$var reg 1 z expected_z $end
$upscope $end
$upscope $end
$enddefinitions $end
#0
$dumpvars
xz
xy
xx
bx w
b0 v
0u
0t
0s
1r
0q
0p
0o
b0 n
b0 m
0l
0k
0j
1i
0h
0g
0f
b0 e
b0 d
0c
0b
0a
1`
0_
0^
0]
b0 \
b0 [
0Z
0Y
0X
1W
0V
0U
0T
b0 S
b0 R
b0 Q
b0 P
b0 O
b0 N
b0 M
b0 L
b0 K
b0 J
b0 I
b0 H
b0 G
b0 F
b0 E
b0 D
b0 C
b0 B
b1 A
b0 @
b0 ?
b0 >
b0 =
b0 <
b0 ;
b0 :
09
b0 8
b0 7
b0 6
05
04
03
b0 2
b0 1
b0 0
b0 /
0.
0-
b0 ,
b0 +
b0 *
x)
x(
x'
x&
x%
b0 $
0#
0"
1!
$end
#1
0%
0)
0&
1z
0'
0(
0y
0x
b0 w
#1000
b1 +
b1 2
b1 D
#2000
b10 +
b10 2
b10 D
#3000
b11 +
b11 2
b11 D
#4000
b100 +
b100 2
b100 D
#5000
b101 +
b101 2
b101 D
#6000
b110 +
b110 2
b110 D
#7000
b111 +
b111 2
b111 D
#8000
b1000 +
b1000 2
b1000 D
#9000
b1001 +
b1001 2
b1001 D
#10000
b1010 +
b1010 2
b1010 D
#11000
b1011 +
b1011 2
b1011 D
#12000
b1100 +
b1100 2
b1100 D
#13000
b1101 +
b1101 2
b1101 D
#14000
b1110 +
b1110 2
b1110 D
#15000
b1111 +
b1111 2
b1111 D
#16000
0!
b1 $
b1 ;
b1 I
1X
1Y
b1 7
b1 K
b1 N
1V
b1 <
b1 >
b1 M
b1 P
b1 :
b1 ?
b1 E
b1 *
b1 0
b1 C
b1 G
b0 +
b0 2
b0 D
#16001
0z
b1 w
#17000
b1 +
b1 2
b1 D
#18000
b10 +
b10 2
b10 D
#19000
b11 +
b11 2
b11 D
#20000
b100 +
b100 2
b100 D
#21000
b101 +
b101 2
b101 D
#22000
b110 +
b110 2
b110 D
#23000
b111 +
b111 2
b111 D
#24000
b1000 +
b1000 2
b1000 D
#25000
b1001 +
b1001 2
b1001 D
#26000
b1010 +
b1010 2
b1010 D
#27000
b1011 +
b1011 2
b1011 D
#28000
b1100 +
b1100 2
b1100 D
#29000
b1101 +
b1101 2
b1101 D
#30000
b1110 +
b1110 2
b1110 D
#31000
b1111 +
b1111 2
b1111 D
#32000
b10 $
b10 ;
b10 I
0X
0Y
1a
1b
b10 7
b10 K
b10 N
0V
1_
b10 <
b10 >
b10 M
b10 P
b10 :
b10 ?
b10 E
b10 *
b10 0
b10 C
b10 G
b0 +
b0 2
b0 D
#32001
b10 w
#33000
b1 +
b1 2
b1 D
#34000
b10 +
b10 2
b10 D
#35000
b11 +
b11 2
b11 D
#36000
b100 +
b100 2
b100 D
#37000
b101 +
b101 2
b101 D
#38000
b110 +
b110 2
b110 D
#39000
b111 +
b111 2
b111 D
#40000
b1000 +
b1000 2
b1000 D
#41000
b1001 +
b1001 2
b1001 D
#42000
b1010 +
b1010 2
b1010 D
#43000
b1011 +
b1011 2
b1011 D
#44000
b1100 +
b1100 2
b1100 D
#45000
b1101 +
b1101 2
b1101 D
#46000
b1110 +
b1110 2
b1110 D
#47000
b1111 +
b1111 2
b1111 D
#48000
b11 $
b11 ;
b11 I
1X
1Y
b11 7
b11 K
b11 N
1V
b11 <
b11 >
b11 M
b11 P
b11 :
b11 ?
b11 E
b11 *
b11 0
b11 C
b11 G
b0 +
b0 2
b0 D
#48001
b11 w
#49000
b1 +
b1 2
b1 D
#50000
b10 +
b10 2
b10 D
#51000
b11 +
b11 2
b11 D
#52000
b100 +
b100 2
b100 D
#53000
b101 +
b101 2
b101 D
#54000
b110 +
b110 2
b110 D
#55000
b111 +
b111 2
b111 D
#56000
b1000 +
b1000 2
b1000 D
#57000
b1001 +
b1001 2
b1001 D
#58000
b1010 +
b1010 2
b1010 D
#59000
b1011 +
b1011 2
b1011 D
#60000
b1100 +
b1100 2
b1100 D
#61000
b1101 +
b1101 2
b1101 D
#62000
b1110 +
b1110 2
b1110 D
#63000
b1111 +
b1111 2
b1111 D
#64000
b100 $
b100 ;
b100 I
0X
0Y
0a
0b
1j
1k
b100 7
b100 K
b100 N
0V
0_
1h
b100 <
b100 >
b100 M
b100 P
b100 :
b100 ?
b100 E
b100 *
b100 0
b100 C
b100 G
b0 +
b0 2
b0 D
#64001
b100 w
#65000
b1 +
b1 2
b1 D
#66000
b10 +
b10 2
b10 D
#67000
b11 +
b11 2
b11 D
#68000
b100 +
b100 2
b100 D
#69000
b101 +
b101 2
b101 D
#70000
b110 +
b110 2
b110 D
#71000
b111 +
b111 2
b111 D
#72000
b1000 +
b1000 2
b1000 D
#73000
b1001 +
b1001 2
b1001 D
#74000
b1010 +
b1010 2
b1010 D
#75000
b1011 +
b1011 2
b1011 D
#76000
b1100 +
b1100 2
b1100 D
#77000
b1101 +
b1101 2
b1101 D
#78000
b1110 +
b1110 2
b1110 D
#79000
b1111 +
b1111 2
b1111 D
#80000
b101 $
b101 ;
b101 I
1X
1Y
b101 7
b101 K
b101 N
1V
b101 <
b101 >
b101 M
b101 P
b101 :
b101 ?
b101 E
b101 *
b101 0
b101 C
b101 G
b0 +
b0 2
b0 D
#80001
b101 w
#81000
b1 +
b1 2
b1 D
#82000
b10 +
b10 2
b10 D
#83000
b11 +
b11 2
b11 D
#84000
b100 +
b100 2
b100 D
#85000
b101 +
b101 2
b101 D
#86000
b110 +
b110 2
b110 D
#87000
b111 +
b111 2
b111 D
#88000
b1000 +
b1000 2
b1000 D
#89000
b1001 +
b1001 2
b1001 D
#90000
b1010 +
b1010 2
b1010 D
#91000
b1011 +
b1011 2
b1011 D
#92000
b1100 +
b1100 2
b1100 D
#93000
b1101 +
b1101 2
b1101 D
#94000
b1110 +
b1110 2
b1110 D
#95000
b1111 +
b1111 2
b1111 D
#96000
b110 $
b110 ;
b110 I
0X
0Y
1a
1b
b110 7
b110 K
b110 N
0V
1_
b110 <
b110 >
b110 M
b110 P
b110 :
b110 ?
b110 E
b110 *
b110 0
b110 C
b110 G
b0 +
b0 2
b0 D
#96001
b110 w
#97000
b1 +
b1 2
b1 D
#98000
b10 +
b10 2
b10 D
#99000
b11 +
b11 2
b11 D
#100000
b100 +
b100 2
b100 D
#101000
b101 +
b101 2
b101 D
#102000
b110 +
b110 2
b110 D
#103000
b111 +
b111 2
b111 D
#104000
b1000 +
b1000 2
b1000 D
#105000
b1001 +
b1001 2
b1001 D
#106000
b1010 +
b1010 2
b1010 D
#107000
b1011 +
b1011 2
b1011 D
#108000
b1100 +
b1100 2
b1100 D
#109000
b1101 +
b1101 2
b1101 D
#110000
b1110 +
b1110 2
b1110 D
#111000
b1111 +
b1111 2
b1111 D
#112000
b111 $
b111 ;
b111 I
1X
1Y
b111 7
b111 K
b111 N
1V
b111 <
b111 >
b111 M
b111 P
b111 :
b111 ?
b111 E
b111 *
b111 0
b111 C
b111 G
b0 +
b0 2
b0 D
#112001
b111 w
#113000
b1 +
b1 2
b1 D
#114000
b10 +
b10 2
b10 D
#115000
b11 +
b11 2
b11 D
#116000
b100 +
b100 2
b100 D
#117000
b101 +
b101 2
b101 D
#118000
b110 +
b110 2
b110 D
#119000
b111 +
b111 2
b111 D
#120000
b1000 +
b1000 2
b1000 D
#121000
b1001 +
b1001 2
b1001 D
#122000
b1010 +
b1010 2
b1010 D
#123000
b1011 +
b1011 2
b1011 D
#124000
b1100 +
b1100 2
b1100 D
#125000
b1101 +
b1101 2
b1101 D
#126000
b1110 +
b1110 2
b1110 D
#127000
b1111 +
b1111 2
b1111 D
#128000
1"
b1000 $
b1000 ;
b1000 I
0X
0Y
0a
0b
0j
0k
1s
1t
b1000 7
b1000 K
b1000 N
0V
0_
0h
1q
b1000 <
b1000 >
b1000 M
b1000 P
b1000 :
b1000 ?
b1000 E
b1000 *
b1000 0
b1000 C
b1000 G
b0 +
b0 2
b0 D
#128001
1y
b1000 w
#129000
b1 +
b1 2
b1 D
#130000
b10 +
b10 2
b10 D
#131000
b11 +
b11 2
b11 D
#132000
b100 +
b100 2
b100 D
#133000
b101 +
b101 2
b101 D
#134000
b110 +
b110 2
b110 D
#135000
b111 +
b111 2
b111 D
#136000
b1000 +
b1000 2
b1000 D
#137000
b1001 +
b1001 2
b1001 D
#138000
b1010 +
b1010 2
b1010 D
#139000
b1011 +
b1011 2
b1011 D
#140000
b1100 +
b1100 2
b1100 D
#141000
b1101 +
b1101 2
b1101 D
#142000
b1110 +
b1110 2
b1110 D
#143000
b1111 +
b1111 2
b1111 D
#144000
b1001 $
b1001 ;
b1001 I
1X
1Y
b1001 7
b1001 K
b1001 N
1V
b1001 <
b1001 >
b1001 M
b1001 P
b1001 :
b1001 ?
b1001 E
b1001 *
b1001 0
b1001 C
b1001 G
b0 +
b0 2
b0 D
#144001
b1001 w
#145000
b1 +
b1 2
b1 D
#146000
b10 +
b10 2
b10 D
#147000
b11 +
b11 2
b11 D
#148000
b100 +
b100 2
b100 D
#149000
b101 +
b101 2
b101 D
#150000
b110 +
b110 2
b110 D
#151000
b111 +
b111 2
b111 D
#152000
b1000 +
b1000 2
b1000 D
#153000
b1001 +
b1001 2
b1001 D
#154000
b1010 +
b1010 2
b1010 D
#155000
b1011 +
b1011 2
b1011 D
#156000
b1100 +
b1100 2
b1100 D
#157000
b1101 +
b1101 2
b1101 D
#158000
b1110 +
b1110 2
b1110 D
#159000
b1111 +
b1111 2
b1111 D
#160000
b1010 $
b1010 ;
b1010 I
0X
0Y
1a
1b
b1010 7
b1010 K
b1010 N
0V
1_
b1010 <
b1010 >
b1010 M
b1010 P
b1010 :
b1010 ?
b1010 E
b1010 *
b1010 0
b1010 C
b1010 G
b0 +
b0 2
b0 D
#160001
b1010 w
#161000
b1 +
b1 2
b1 D
#162000
b10 +
b10 2
b10 D
#163000
b11 +
b11 2
b11 D
#164000
b100 +
b100 2
b100 D
#165000
b101 +
b101 2
b101 D
#166000
b110 +
b110 2
b110 D
#167000
b111 +
b111 2
b111 D
#168000
b1000 +
b1000 2
b1000 D
#169000
b1001 +
b1001 2
b1001 D
#170000
b1010 +
b1010 2
b1010 D
#171000
b1011 +
b1011 2
b1011 D
#172000
b1100 +
b1100 2
b1100 D
#173000
b1101 +
b1101 2
b1101 D
#174000
b1110 +
b1110 2
b1110 D
#175000
b1111 +
b1111 2
b1111 D
#176000
b1011 $
b1011 ;
b1011 I
1X
1Y
b1011 7
b1011 K
b1011 N
1V
b1011 <
b1011 >
b1011 M
b1011 P
b1011 :
b1011 ?
b1011 E
b1011 *
b1011 0
b1011 C
b1011 G
b0 +
b0 2
b0 D
#176001
b1011 w
#177000
b1 +
b1 2
b1 D
#178000
b10 +
b10 2
b10 D
#179000
b11 +
b11 2
b11 D
#180000
b100 +
b100 2
b100 D
#181000
b101 +
b101 2
b101 D
#182000
b110 +
b110 2
b110 D
#183000
b111 +
b111 2
b111 D
#184000
b1000 +
b1000 2
b1000 D
#185000
b1001 +
b1001 2
b1001 D
#186000
b1010 +
b1010 2
b1010 D
#187000
b1011 +
b1011 2
b1011 D
#188000
b1100 +
b1100 2
b1100 D
#189000
b1101 +
b1101 2
b1101 D
#190000
b1110 +
b1110 2
b1110 D
#191000
b1111 +
b1111 2
b1111 D
#192000
b1100 $
b1100 ;
b1100 I
0X
0Y
0a
0b
1j
1k
b1100 7
b1100 K
b1100 N
0V
0_
1h
b1100 <
b1100 >
b1100 M
b1100 P
b1100 :
b1100 ?
b1100 E
b1100 *
b1100 0
b1100 C
b1100 G
b0 +
b0 2
b0 D
#192001
b1100 w
#193000
b1 +
b1 2
b1 D
#194000
b10 +
b10 2
b10 D
#195000
b11 +
b11 2
b11 D
#196000
b100 +
b100 2
b100 D
#197000
b101 +
b101 2
b101 D
#198000
b110 +
b110 2
b110 D
#199000
b111 +
b111 2
b111 D
#200000
b1000 +
b1000 2
b1000 D
#201000
b1001 +
b1001 2
b1001 D
#202000
b1010 +
b1010 2
b1010 D
#203000
b1011 +
b1011 2
b1011 D
#204000
b1100 +
b1100 2
b1100 D
#205000
b1101 +
b1101 2
b1101 D
#206000
b1110 +
b1110 2
b1110 D
#207000
b1111 +
b1111 2
b1111 D
#208000
b1101 $
b1101 ;
b1101 I
1X
1Y
b1101 7
b1101 K
b1101 N
1V
b1101 <
b1101 >
b1101 M
b1101 P
b1101 :
b1101 ?
b1101 E
b1101 *
b1101 0
b1101 C
b1101 G
b0 +
b0 2
b0 D
#208001
b1101 w
#209000
b1 +
b1 2
b1 D
#210000
b10 +
b10 2
b10 D
#211000
b11 +
b11 2
b11 D
#212000
b100 +
b100 2
b100 D
#213000
b101 +
b101 2
b101 D
#214000
b110 +
b110 2
b110 D
#215000
b111 +
b111 2
b111 D
#216000
b1000 +
b1000 2
b1000 D
#217000
b1001 +
b1001 2
b1001 D
#218000
b1010 +
b1010 2
b1010 D
#219000
b1011 +
b1011 2
b1011 D
#220000
b1100 +
b1100 2
b1100 D
#221000
b1101 +
b1101 2
b1101 D
#222000
b1110 +
b1110 2
b1110 D
#223000
b1111 +
b1111 2
b1111 D
#224000
b1110 $
b1110 ;
b1110 I
0X
0Y
1a
1b
b1110 7
b1110 K
b1110 N
0V
1_
b1110 <
b1110 >
b1110 M
b1110 P
b1110 :
b1110 ?
b1110 E
b1110 *
b1110 0
b1110 C
b1110 G
b0 +
b0 2
b0 D
#224001
b1110 w
#225000
b1 +
b1 2
b1 D
#226000
b10 +
b10 2
b10 D
#227000
b11 +
b11 2
b11 D
#228000
b100 +
b100 2
b100 D
#229000
b101 +
b101 2
b101 D
#230000
b110 +
b110 2
b110 D
#231000
b111 +
b111 2
b111 D
#232000
b1000 +
b1000 2
b1000 D
#233000
b1001 +
b1001 2
b1001 D
#234000
b1010 +
b1010 2
b1010 D
#235000
b1011 +
b1011 2
b1011 D
#236000
b1100 +
b1100 2
b1100 D
#237000
b1101 +
b1101 2
b1101 D
#238000
b1110 +
b1110 2
b1110 D
#239000
b1111 +
b1111 2
b1111 D
#240000
b1111 $
b1111 ;
b1111 I
1X
1Y
b1111 7
b1111 K
b1111 N
1V
b1111 <
b1111 >
b1111 M
b1111 P
b1111 :
b1111 ?
b1111 E
b1111 *
b1111 0
b1111 C
b1111 G
b0 +
b0 2
b0 D
#240001
b1111 w
#241000
b1 +
b1 2
b1 D
#242000
b10 +
b10 2
b10 D
#243000
b11 +
b11 2
b11 D
#244000
b100 +
b100 2
b100 D
#245000
b101 +
b101 2
b101 D
#246000
b110 +
b110 2
b110 D
#247000
b111 +
b111 2
b111 D
#248000
b1000 +
b1000 2
b1000 D
#249000
b1001 +
b1001 2
b1001 D
#250000
b1010 +
b1010 2
b1010 D
#251000
b1011 +
b1011 2
b1011 D
#252000
b1100 +
b1100 2
b1100 D
#253000
b1101 +
b1101 2
b1101 D
#254000
b1110 +
b1110 2
b1110 D
#255000
b1111 +
b1111 2
b1111 D
#256000
0!
0"
0X
0Y
0a
0b
0j
0k
0s
0t
0V
0_
0h
0q
b1 $
b1 ;
b1 I
b0 <
b0 >
b0 M
b0 P
b1 7
b1 K
b1 N
0#
b0 :
b0 ?
b0 E
1-
b0 *
b0 0
b0 C
b0 G
b0 +
b0 2
b0 D
#256001
0y
b1 w
#257000
b1 +
b1 2
b1 D
#258000
b10 +
b10 2
b10 D
#259000
b11 +
b11 2
b11 D
#260000
b100 +
b100 2
b100 D
#261000
b101 +
b101 2
b101 D
#262000
b110 +
b110 2
b110 D
#263000
b111 +
b111 2
b111 D
#264000
b1000 +
b1000 2
b1000 D
#265000
b1001 +
b1001 2
b1001 D
#266000
b1010 +
b1010 2
b1010 D
#267000
b1011 +
b1011 2
b1011 D
#268000
b1100 +
b1100 2
b1100 D
#269000
b1101 +
b1101 2
b1101 D
#270000
b1110 +
b1110 2
b1110 D
#271000
b1111 +
b1111 2
b1111 D
#272000
b10 $
b10 ;
b10 I
1X
1Y
b10 7
b10 K
b10 N
1V
b1 <
b1 >
b1 M
b1 P
b1 :
b1 ?
b1 E
b1 *
b1 0
b1 C
b1 G
b0 +
b0 2
b0 D
#272001
b10 w
#273000
b1 +
b1 2
b1 D
#274000
b10 +
b10 2
b10 D
#275000
b11 +
b11 2
b11 D
#276000
b100 +
b100 2
b100 D
#277000
b101 +
b101 2
b101 D
#278000
b110 +
b110 2
b110 D
#279000
b111 +
b111 2
b111 D
#280000
b1000 +
b1000 2
b1000 D
#281000
b1001 +
b1001 2
b1001 D
#282000
b1010 +
b1010 2
b1010 D
#283000
b1011 +
b1011 2
b1011 D
#284000
b1100 +
b1100 2
b1100 D
#285000
b1101 +
b1101 2
b1101 D
#286000
b1110 +
b1110 2
b1110 D
#287000
b1111 +
b1111 2
b1111 D
#288000
b11 $
b11 ;
b11 I
0X
0Y
1a
1b
b11 7
b11 K
b11 N
0V
1_
b10 <
b10 >
b10 M
b10 P
b10 :
b10 ?
b10 E
b10 *
b10 0
b10 C
b10 G
b0 +
b0 2
b0 D
#288001
b11 w
#289000
b1 +
b1 2
b1 D
#290000
b10 +
b10 2
b10 D
#291000
b11 +
b11 2
b11 D
#292000
b100 +
b100 2
b100 D
#293000
b101 +
b101 2
b101 D
#294000
b110 +
b110 2
b110 D
#295000
b111 +
b111 2
b111 D
#296000
b1000 +
b1000 2
b1000 D
#297000
b1001 +
b1001 2
b1001 D
#298000
b1010 +
b1010 2
b1010 D
#299000
b1011 +
b1011 2
b1011 D
#300000
b1100 +
b1100 2
b1100 D
#301000
b1101 +
b1101 2
b1101 D
#302000
b1110 +
b1110 2
b1110 D
#303000
b1111 +
b1111 2
b1111 D
#304000
b100 $
b100 ;
b100 I
1X
1Y
b100 7
b100 K
b100 N
1V
b11 <
b11 >
b11 M
b11 P
b11 :
b11 ?
b11 E
b11 *
b11 0
b11 C
b11 G
b0 +
b0 2
b0 D
#304001
b100 w
#305000
b1 +
b1 2
b1 D
#306000
b10 +
b10 2
b10 D
#307000
b11 +
b11 2
b11 D
#308000
b100 +
b100 2
b100 D
#309000
b101 +
b101 2
b101 D
#310000
b110 +
b110 2
b110 D
#311000
b111 +
b111 2
b111 D
#312000
b1000 +
b1000 2
b1000 D
#313000
b1001 +
b1001 2
b1001 D
#314000
b1010 +
b1010 2
b1010 D
#315000
b1011 +
b1011 2
b1011 D
#316000
b1100 +
b1100 2
b1100 D
#317000
b1101 +
b1101 2
b1101 D
#318000
b1110 +
b1110 2
b1110 D
#319000
b1111 +
b1111 2
b1111 D
#320000
b101 $
b101 ;
b101 I
0X
0Y
0a
0b
1j
1k
b101 7
b101 K
b101 N
0V
0_
1h
b100 <
b100 >
b100 M
b100 P
b100 :
b100 ?
b100 E
b100 *
b100 0
b100 C
b100 G
b0 +
b0 2
b0 D
#320001
b101 w
