fa.v
module fa(output wire c_out, sum, input wire a, b, c_in);
   assign (c_out, sum) = a + b + c_in;
endmodule

fa_tb.v
`timescale 1 ns /10 ps

module fa_tb;

reg test_c_out;
wire test_sum;
wire test_a, test_b, test_c_in;

fa fa_1(test_c_out, test_sum, test_a, test_b, test_c_in);

initial
begin
$monitor("tiempo=%0d a=%b b=%b c_in=%b c_out=%b sum=%b", $time, test_a, test_b, test_c_in, test_c_out, test_sum);
$dumpfile("fa_tb.vcd");
$dumpvars;

//vector de test 0
test_a = 1'b0;
test_b = 1'b0;
test_c_in = 1'b0;
#20;

//vector de test 1
test_a = 1'b1;
test_b = 1'b0;
test_c_in = 1'b0;
#20;

//vector de test 2
test_a = 1'b0;
test_b = 1'b1;
test_c_in = 1'b0;
#20;

//vector de test 3
test_a = 1'b1;
test_b = 1'b1;
test_c_in = 1'b0;
#20;

//vector de test 4
test_a = 1'b0;
test_b = 1'b0;
test_c_in = 1'b1;
#20;

//vector de test 5
test_a = 1'b1;
test_b = 1'b0;
test_c_in = 1'b1;
#20;

//vector de test 6
test_a = 1'b0;
test_b = 1'b1;
test_c_in = 1'b1;
#20;

//vector de test 7
test_a = 1'b1;
test_b = 1'b1;
test_c_in = 1'b1;

$finish;


end


endmodule

fa_tb.vcd
$date
	Sun Oct 22 13:33:32 2023
$end
$version
	Icarus Verilog
$end
$timescale
	10ps
$end
$scope module fa_tb $end
$var wire 1 ! test_sum $end
$var wire 1 " test_c_out $end
$var reg 1 # test_a $end
$var reg 1 $ test_b $end
$var reg 1 % test_c_in $end
$scope module fa_1 $end
$var wire 1 # a $end
$var wire 1 $ b $end
$var wire 1 % c_in $end
$var wire 1 ! sum $end
$var wire 1 " c_out $end
$upscope $end
$upscope $end
$enddefinitions $end
#0
$dumpvars
0%
0$
0#
0"
0!
$end
#2000
1!
1#
#4000
1$
0#
#6000
0!
1"
1#
#8000
1!
0"
1%
0$
0#
#10000
0!
1"
1#
#12000
1$
0#
#14000
1!
1#
