mux4.v

module mux4(output reg out, input wire a, b, c, d, input wire [1:0] S);

    always @(*)
    begin
    case (S)
        2'b00: out = a;
        2'b01: out = b;
        2'b10: out = c;
        2'b11: out = d;
    endcase
    end

endmodule

mux4_tb.v
`timescale  1 ns/ 10 ps

module mux4_tb;

reg test_a, test_b, test_c, test_d;

wire test_out;
reg [1:0] test_s;

mux4 mux4_1 (test_out, test_a, test_b, test_c, test_d, test_s);



initial
begin
  $monitor("tiempo=%0d a=%b b=%b c=%b d=%b s=%b", $time, test_a, test_b, test_c, test_d, test_s);
  $dumpfile("ha_v1_tb.vcd");
  $dumpvars;

  //vector de test 0
  test_a = 1'b0;
  test_b = 1'b0;
  test_c = 1'b0;
  test_d = 1'b0;
  test_s = 2'b00;
  #20;

  //vector de test 1
  test_a = 1'b1;
  test_b = 1'b0;
  test_c = 1'b0;
  test_d = 1'b0;
  test_s = 2'b00;
  #20;

  //vector de test 2
  test_a = 1'b0;
  test_b = 1'b1;
  test_c = 1'b0;
  test_d = 1'b0;
  test_s = 2'b01;
  #20;

  //vector de test 3
  test_a = 1'b1;
  test_b = 1'b1;
  test_c = 1'b0;
  test_d = 1'b0;
  test_s = 2'b01;
  #20;

  //vector de test 4
  test_a = 1'b0;
  test_b = 1'b0;
  test_c = 1'b1;
  test_d = 1'b0;
  test_s = 2'b10;
  #20;

  //vector de test 5
  test_a = 1'b1;
  test_b = 1'b0;
  test_c = 1'b1;
  test_d = 1'b0;
  test_s = 2'b10;
  #20;

    //vector de test 5
  test_a = 1'b0;
  test_b = 1'b1;
  test_c = 1'b1;
  test_d = 1'b0;
  test_s = 2'b11;
  #20;

  //vector de test 6
  test_a = 1'b1;
  test_b = 1'b1;
  test_c = 1'b1;
  test_d = 1'b0;
  test_s = 2'b11;
  #20;

  //vector de test 0
  test_a = 1'b0;
  test_b = 1'b0;
  test_c = 1'b0;
  test_d = 1'b1;
  test_s = 2'b00;
  #20;

  //vector de test 1
  test_a = 1'b1;
  test_b = 1'b0;
  test_c = 1'b0;
  test_d = 1'b1;
  test_s = 2'b00;
  #20;

  //vector de test 2
  test_a = 1'b0;
  test_b = 1'b1;
  test_c = 1'b0;
  test_d = 1'b1;
  test_s = 2'b01;
  #20;

  //vector de test 3
  test_a = 1'b1;
  test_b = 1'b1;
  test_c = 1'b0;
  test_d = 1'b1;
  test_s = 2'b01;
  #20;

  //vector de test 4
  test_a = 1'b0;
  test_b = 1'b0;
  test_c = 1'b1;
  test_d = 1'b1;
  test_s = 2'b10;
  #20;

  //vector de test 5
  test_a = 1'b1;
  test_b = 1'b0;
  test_c = 1'b1;
  test_d = 1'b1;
  test_s = 2'b10;
  #20;

    //vector de test 5
  test_a = 1'b0;
  test_b = 1'b1;
  test_c = 1'b1;
  test_d = 1'b0;
  test_s = 2'b11;
  #20;

  //vector de test 6
  test_a = 1'b1;
  test_b = 1'b1;
  test_c = 1'b1;
  test_d = 1'b1;
  test_s = 2'b11;
  #20;
 
  $finish;  //fin simulacion

end
endmodule

ha_v1_tb.vcd
$date
	Wed Oct 18 13:19:03 2023
$end
$version
	Icarus Verilog
$end
$timescale
	10ps
$end
$scope module mux4_tb $end
$var wire 1 ! test_out $end
$var reg 1 " test_a $end
$var reg 1 # test_b $end
$var reg 1 $ test_c $end
$var reg 1 % test_d $end
$var reg 2 & test_s [1:0] $end
$scope module mux4_1 $end
$var wire 2 ' S [1:0] $end
$var wire 1 " a $end
$var wire 1 # b $end
$var wire 1 $ c $end
$var wire 1 % d $end
$var reg 1 ! out $end
$upscope $end
$upscope $end
$enddefinitions $end
#0
$dumpvars
b0 '
b0 &
0%
0$
0#
0"
0!
$end
#2000
1!
1"
#4000
0!
b1 &
b1 '
1#
0"
#6000
1"
#8000
b10 &
b10 '
1$
0#
0"
#10000
1"
#12000
b11 &
b11 '
1#
0"
#14000
1"
#16000
b0 &
b0 '
1%
0$
0#
0"
#18000
1!
1"
#20000
0!
b1 &
b1 '
1#
0"
#22000
1"
#24000
b10 &
b10 '
1$
0#
0"
#26000
1"
#28000
b11 &
b11 '
0%
1#
0"
#30000
1!
1%
1"
